{"commitInfo":{"timestamp":1782693251020,"operation":"STREAMING UPDATE","operationParameters":{"outputMode":"Append","queryId":"d8538d3e-e2a6-4c10-92b2-679c2ada58f4","epochId":"1765"},"readVersion":1764,"isolationLevel":"Serializable","isBlindAppend":true,"operationMetrics":{"numRemovedFiles":"0","numOutputRows":"0","numOutputBytes":"2329","numAddedFiles":"0"},"engineInfo":"Apache-Spark/3.5.6 Delta-Lake/3.2.1","txnId":"18eef82d-aa8c-4852-97b6-c9907c1004e8"}}
{"txn":{"appId":"d8538d3e-e2a6-4c10-92b2-679c2ada58f4","version":1765,"lastUpdated":1782693251020}}
