{"commitInfo":{"timestamp":1782704161921,"operation":"STREAMING UPDATE","operationParameters":{"outputMode":"Append","queryId":"d8538d3e-e2a6-4c10-92b2-679c2ada58f4","epochId":"5040"},"readVersion":5039,"isolationLevel":"Serializable","isBlindAppend":true,"operationMetrics":{"numRemovedFiles":"0","numOutputRows":"0","numOutputBytes":"2329","numAddedFiles":"0"},"engineInfo":"Apache-Spark/3.5.6 Delta-Lake/3.2.1","txnId":"ac57ea81-23ef-41b8-9750-a1d449107048"}}
{"txn":{"appId":"d8538d3e-e2a6-4c10-92b2-679c2ada58f4","version":5040,"lastUpdated":1782704161921}}
