{"commitInfo":{"timestamp":1782699732354,"operation":"STREAMING UPDATE","operationParameters":{"outputMode":"Append","queryId":"d8538d3e-e2a6-4c10-92b2-679c2ada58f4","epochId":"4463"},"readVersion":4462,"isolationLevel":"Serializable","isBlindAppend":true,"operationMetrics":{"numRemovedFiles":"0","numOutputRows":"0","numOutputBytes":"2329","numAddedFiles":"0"},"engineInfo":"Apache-Spark/3.5.6 Delta-Lake/3.2.1","txnId":"f8096c5e-d30d-4461-806b-6869219b3028"}}
{"txn":{"appId":"d8538d3e-e2a6-4c10-92b2-679c2ada58f4","version":4463,"lastUpdated":1782699732353}}
