{"commitInfo":{"timestamp":1782695362452,"operation":"STREAMING UPDATE","operationParameters":{"outputMode":"Append","queryId":"d8538d3e-e2a6-4c10-92b2-679c2ada58f4","epochId":"2687"},"readVersion":2686,"isolationLevel":"Serializable","isBlindAppend":true,"operationMetrics":{"numRemovedFiles":"0","numOutputRows":"0","numOutputBytes":"2329","numAddedFiles":"0"},"engineInfo":"Apache-Spark/3.5.6 Delta-Lake/3.2.1","txnId":"a02dad51-ac1f-4486-99d6-999ce971e323"}}
{"txn":{"appId":"d8538d3e-e2a6-4c10-92b2-679c2ada58f4","version":2687,"lastUpdated":1782695362452}}
