{"commitInfo":{"timestamp":1782699080128,"operation":"STREAMING UPDATE","operationParameters":{"outputMode":"Append","queryId":"d8538d3e-e2a6-4c10-92b2-679c2ada58f4","epochId":"4213"},"readVersion":4212,"isolationLevel":"Serializable","isBlindAppend":true,"operationMetrics":{"numRemovedFiles":"0","numOutputRows":"0","numOutputBytes":"2329","numAddedFiles":"0"},"engineInfo":"Apache-Spark/3.5.6 Delta-Lake/3.2.1","txnId":"f49a4f3b-e8d8-4b59-b989-6286f13c2aca"}}
{"txn":{"appId":"d8538d3e-e2a6-4c10-92b2-679c2ada58f4","version":4213,"lastUpdated":1782699080128}}
